aplnb/__init__.py
aplnb/_modidx.py
aplnb/core.py
aplnb/lb.js
aplnb-0.0.2.dist-info/LICENSE
aplnb-0.0.2.dist-info/METADATA
aplnb-0.0.2.dist-info/WHEEL
aplnb-0.0.2.dist-info/entry_points.txt
aplnb-0.0.2.dist-info/top_level.txt
aplnb-0.0.2.dist-info/RECORD
